gdsvd/__init__.py
gdsvd/svd.py
gdsvd/utils.py
gdsvd-0.1.dist-info/METADATA
gdsvd-0.1.dist-info/WHEEL
gdsvd-0.1.dist-info/top_level.txt
gdsvd-0.1.dist-info/RECORD
