Metadata-Version: 2.1
Name: gdsvd
Version: 0.1
Summary: A package for gradient-based SVD
Home-page: https://github.com/matrix-completion/gdsvd
Author: Emily Gan
Author-email: emily.gan496@gmail.com
License: UNKNOWN
Platform: UNKNOWN
Classifier: Programming Language :: Python :: 3
Classifier: License :: OSI Approved :: MIT License
Classifier: Operating System :: OS Independent
Requires-Python: >=3.6
Requires-Dist: numpy
Requires-Dist: scipy
